[
{
"id": 1,
"question": "সর্বদলীয় কেন্দ্রীয় রাষ্ট্রভাষা সংগ্রাম পরিষদ গঠিত হয় কবে?",
"options": {
"a": "৩০ জানুয়ারি ১৯৫২",
"b": "৩১ জানুয়ারি ১৯৫২",
"c": "২১ ফেব্রুয়ারি ১৯৫২",
"d": "২ মার্চ ১৯৪৮"
},
"correct_answer": "b",
"explanation": "১৯৫২ সালের ৩১ জানুয়ারি ঢাকা বার লাইব্রেরি মিলনায়তনে মাওলানা ভাসানীর সভাপতিত্বে এই পরিষদ গঠিত হয়।"
},
{
"id": 2,
"question": "বাংলাদেশের সংবিধানের কত নম্বর অনুচ্ছেদে 'জাতীয় সংগীত, পতাকা ও প্রতীক' সম্পর্কে বলা হয়েছে?",
"options": {
"a": "২ নম্বর",
"b": "৩ নম্বর",
"c": "৪ নম্বর",
"d": "৫ নম্বর"
},
"correct_answer": "c",
"explanation": "সংবিধানের ৪ নম্বর অনুচ্ছেদে জাতীয় সংগীত, পতাকা ও প্রতীক সম্পর্কে আলোচনা করা হয়েছে।"
},
{
"id": 3,
"question": "মুক্তিযুদ্ধে 'সিলেট' কত নম্বর সেক্টরের অধীনে ছিল?",
"options": {
"a": "২ নম্বর",
"b": "৩ নম্বর",
"c": "৪ ও ৫ নম্বর",
"d": "১ নম্বর"
},
"correct_answer": "c",
"explanation": "সিলেট জেলার পূর্বাঞ্চল ৪ নম্বর এবং পশ্চিমাঞ্চল ৫ নম্বর সেক্টরের অধীনে ছিল।"
},
{
"id": 4,
"question": "বঙ্গবন্ধু শেখ মুজিবুর রহমানকে 'জাতির জনক' ঘোষণা করা হয় কবে?",
"options": {
"a": "৩ মার্চ ১৯৭১",
"b": "৭ মার্চ ১৯৭১",
"c": "১০ জানুয়ারি ১৯৭২",
"d": "২৬ মার্চ ১৯৭১"
},
"correct_answer": "a",
"explanation": "৩ মার্চ ১৯৭১ সালে পল্টন ময়দানে আ স ম আবদুর রব বঙ্গবন্ধুকে জাতির জনক ঘোষণা করেন।"
},
{
"id": 5,
"question": "বাংলাদেশের একমাত্র পাহাড়ি দ্বীপ কোনটি?",
"options": {
"a": "সেন্টমার্টিন",
"b": "মহেশখালী",
"c": "কুতুবদিয়া",
"d": "সন্দ্বীপ"
},
"correct_answer": "b",
"explanation": "মহেশখালী বাংলাদেশের একমাত্র পাহাড়ি দ্বীপ যা কক্সবাজার জেলায় অবস্থিত।"
},
{
"id": 6,
"question": "তিলপাড়া ব্যারেজ কোন নদীর ওপর অবস্থিত?",
"options": {
"a": "সুরমা",
"b": "কুশিয়ারা",
"c": "মনু",
"d": "খোয়াই"
},
"correct_answer": "b",
"explanation": "তিলপাড়া ব্যারেজ সিলেট জেলার কুশিয়ারা নদীর ওপর নির্মিত।"
},
{
"id": 7,
"question": "বাংলাদেশের সংবিধান কার্যকর হয় কোন তারিখে?",
"options": {
"a": "৪ নভেম্বর ১৯৭২",
"b": "১৬ ডিসেম্বর ১৯৭২",
"c": "২৬ মার্চ ১৯৭২",
"d": "১০ এপ্রিল ১৯৭২"
},
"correct_answer": "b",
"explanation": "১৯৭২ সালের ১৬ ডিসেম্বর থেকে বাংলাদেশের সংবিধান কার্যকর করা হয়।"
},
{
"id": 8,
"question": "ঐতিহাসিক 'ছয় দফা' দিবস পালন করা হয় কবে?",
"options": {
"a": "৫ ফেব্রুয়ারি",
"b": "৭ জুন",
"c": "২৩ মার্চ",
"d": "১৭ এপ্রিল"
},
"correct_answer": "b",
"explanation": "১৯৬৬ সালের ৭ জুন ছয় দফার সমর্থনে হরতাল পালিত হয়, তাই এই দিনটি ছয় দফা দিবস।"
},
{
"id": 9,
"question": "বাংলাদেশের কোন রাষ্ট্রীয় অনুষ্ঠানে জাতীয় সংগীতের কয়টি চরণ বাজানো হয়?",
"options": {
"a": "প্রথম ৪টি",
"b": "প্রথম ৫টি",
"c": "সবগুলো",
"d": "প্রথম ১০টি"
},
"correct_answer": "a",
"explanation": "যেকোনো রাষ্ট্রীয় অনুষ্ঠানে জাতীয় সংগীতের প্রথম ৪ চরণ বাজানো হয়, গাওয়ার সময় ১০ চরণ।"
},
{
"id": 10,
"question": "বাংলাদেশের বৃহত্তম হাওর কোনটি?",
"options": {
"a": "চলন বিল",
"b": "হাকালুকি",
"c": "টাঙ্গুয়ার হাওর",
"d": "হাইল হাওর"
},
"correct_answer": "b",
"explanation": "হাকালুকি হাওর বাংলাদেশের বৃহত্তম হাওর, যা মৌলভীবাজার ও সিলেট জেলায় বিস্তৃত।"
},
{
"id": 11,
"question": "জাতীয় সংসদের প্রথম স্পিকার কে ছিলেন?",
"options": {
"a": "আবদুল হামিদ",
"b": "হুমায়ুন রশীদ চৌধুরী",
"c": "শাহ আব্দুল হামিদ",
"d": "মোহাম্মদ উল্লাহ"
},
"correct_answer": "c",
"explanation": "গণপরিষদ ও জাতীয় সংসদের প্রথম স্পিকার ছিলেন শাহ আব্দুল হামিদ।"
},
{
"id": 12,
"question": "মুজিবনগর সরকারের অর্থমন্ত্রী কে ছিলেন?",
"options": {
"a": "সৈয়দ নজরুল ইসলাম",
"b": "তাজউদ্দীন আহমদ",
"c": "এম মনসুর আলী",
"d": "এ এইচ এম কামারুজ্জামান"
},
"correct_answer": "c",
"explanation": "এম মনসুর আলী ছিলেন স্বাধীন বাংলাদেশের প্রথম অস্থায়ী (মুজিবনগর) সরকারের অর্থমন্ত্রী।"
},
{
"id": 13,
"question": "বাংলাদেশের জিডিপিতে কোন খাতের অবদান বর্তমানে সবচেয়ে বেশি?",
"options": {
"a": "কৃষি",
"b": "শিল্প",
"c": "সেবা",
"d": "প্রবাসী আয়"
},
"correct_answer": "c",
"explanation": "বাংলাদেশের জিডিপিতে সেবা (Service) খাতের অবদান ৫৩% এর উপরে।"
},
{
"id": 14,
"question": "ইউনেস্কো সুন্দরবনকে 'ওয়ার্ল্ড হেরিটেজ সাইট' হিসেবে ঘোষণা করে কবে?",
"options": {
"a": "৬ ডিসেম্বর ১৯৯৭",
"b": "২১ ফেব্রুয়ারি ১৯৯৯",
"c": "১৫ আগস্ট ১৯৭৫",
"d": "২০ মে ১৯৯৬"
},
"correct_answer": "a",
"explanation": "৬ ডিসেম্বর ১৯৯৭ সালে সুন্দরবন ইউনেস্কোর ৭৯৮তম বিশ্ব ঐতিহ্য হিসেবে স্বীকৃতি পায়।"
},
{
"id": 15,
"question": "বাংলাদেশের প্রথম ভূ-উপগ্রহ কেন্দ্র কোনটি?",
"options": {
"a": "তালিবাবাদ",
"b": "বেতবুনিয়া",
"c": "মহাখালী",
"d": "সিলেট"
},
"correct_answer": "b",
"explanation": "রাঙামাটির বেতবুনিয়ায় ১৯৭৫ সালে প্রথম ভূ-উপগ্রহ কেন্দ্রটি উদ্বোধন করা হয়।"
},
{
"id": 16,
"question": "সংবিধানের কোন সংশোধনীকে 'প্রথম বৈপ্লবিক সংশোধনী' বলা হয়?",
"options": {
"a": "চতুর্থ",
"b": "পঞ্চম",
"c": "সপ্তম",
"d": "ত্রয়োদশ"
},
"correct_answer": "a",
"explanation": "চতুর্থ সংশোধনীর মাধ্যমে সংসদীয় পদ্ধতি পরিবর্তন করে রাষ্ট্রপতি শাসিত সরকার ব্যবস্থা চালু হয়।"
},
{
"id": 17,
"question": "বাংলাদেশের সবচেয়ে বড় স্থলবন্দর কোনটি?",
"options": {
"a": "হিলি",
"b": "বেনাপোল",
"c": "বুড়িমারী",
"d": "তামাবিল"
},
"correct_answer": "b",
"explanation": "যশোরের বেনাপোল বাংলাদেশের বৃহত্তম ও প্রধান স্থলবন্দর।"
},
{
"id": 18,
"question": "বাংলাপিডিয়া'র প্রকাশক কোন প্রতিষ্ঠান?",
"options": {
"a": "বাংলা একাডেমি",
"b": "এশিয়াটিক সোসাইটি",
"c": "ঢাকা বিশ্ববিদ্যালয়",
"d": "জাতীয় জাদুঘর"
},
"correct_answer": "b",
"explanation": "বাংলাদেশ এশিয়াটিক সোসাইটি বাংলাপিডিয়া বা বাংলাদেশ জাতীয় জ্ঞানকোষ প্রকাশ করে।"
},
{
"id": 19,
"question": "মুক্তিযুদ্ধে বীরত্বসূচক উপাধি 'বীরশ্রেষ্ঠ' কতজনকে দেওয়া হয়েছে?",
"options": {
"a": "৭ জন",
"b": "৬৮ জন",
"c": "১৭৫ জন",
"d": "৪২৬ জন"
},
"correct_answer": "a",
"explanation": "সর্বোচ্চ বীরত্বসূচক উপাধি বীরশ্রেষ্ঠ দেওয়া হয়েছে ৭ জনকে।"
},
{
"id": 20,
"question": "চর আলেকজান্ডার কোথায় অবস্থিত?",
"options": {
"a": "ভোলা",
"b": "লক্ষ্মীপুর",
"c": "নোয়াখালী",
"d": "বরগুনা"
},
"correct_answer": "b",
"explanation": "চর আলেকজান্ডার লক্ষ্মীপুর জেলার রামগতি উপজেলায় অবস্থিত।"
},
{
"id": 21,
"question": "বাংলাদেশের প্রথম নারী প্রধানমন্ত্রীর নাম কী?",
"options": {
"a": "বেগম খালেদা জিয়া",
"b": "শেখ হাসিনা",
"c": "শিরীন শারমিন চৌধুরী",
"d": "বেগম রোকেয়া"
},
"correct_answer": "a",
"explanation": "১৯৯১ সালে বেগম খালেদা জিয়া বাংলাদেশের প্রথম নারী প্রধানমন্ত্রী হিসেবে শপথ নেন।"
},
{
"id": 22,
"question": "পদ্মা সেতু উদ্বোধনের তারিখ কোনটি?",
"options": {
"a": "২৫ জুন ২০২২",
"b": "২৬ জুন ২০২২",
"c": "৪ জুলাই ২০২২",
"d": "১৬ ডিসেম্বর ২০২১"
},
"correct_answer": "a",
"explanation": "২০২২ সালের ২৫ জুন প্রধানমন্ত্রী শেখ হাসিনা পদ্মা বহুমুখী সেতু উদ্বোধন করেন।"
},
{
"id": 23,
"question": "বাংলাদেশের কোন জেলাটি ভারতের সীমানা দ্বারা তিন দিকে বেষ্টিত?",
"options": {
"a": "দিনাজপুর",
"b": "সাতক্ষীরা",
"c": "কুমিল্লা",
"d": "লালমনিরহাট"
},
"correct_answer": "d",
"explanation": "লালমনিরহাট জেলাটি ভারতের সাথে তিন দিকে সীমান্ত ভাগ করে নেয়।"
},
{
"id": 24,
"question": "বাংলা একাডেমি কত সালে প্রতিষ্ঠিত হয়?",
"options": {
"a": "১৯৫২",
"b": "১৯৫৪",
"c": "১৯৫৫",
"d": "১৯৬০"
},
"correct_answer": "c",
"explanation": "৩ ডিসেম্বর ১৯৫৫ সালে ভাষা আন্দোলনের প্রেক্ষাপটে বাংলা একাডেমি প্রতিষ্ঠিত হয়।"
},
{
"id": 25,
"question": "বাংলাদেশের জাতীয় সংসদের আসন সংখ্যা কতটি?",
"options": {
"a": "৩০০টি",
"b": "৩৩০টি",
"c": "৩৫০টি",
"d": "৪০০টি"
},
"correct_answer": "c",
"explanation": "৩০০টি নির্বাচিত আসন এবং ৫০টি সংরক্ষিত মহিলা আসন নিয়ে মোট ৩৫০টি আসন।"
},
{
"id": 26,
"question": "বাংলাদেশের কেন্দ্রীয় ব্যাংকের নাম কী?",
"options": {
"a": "সোনালী ব্যাংক",
"b": "বাংলাদেশ ব্যাংক",
"c": "জাতীয় ব্যাংক",
"d": "রিজার্ভ ব্যাংক অব বাংলাদেশ"
},
"correct_answer": "b",
"explanation": "বাংলাদেশ ব্যাংক হলো বাংলাদেশের কেন্দ্রীয় ব্যাংক যা ১৯৭১ সালের ১৬ ডিসেম্বর প্রতিষ্ঠিত হয়।"
},
{
"id": 27,
"question": "বঙ্গবন্ধুর লেখা দ্বিতীয় বইটির নাম কী?",
"options": {
"a": "অসমাপ্ত আত্মজীবনী",
"b": "কারাগারের রোজনামচা",
"c": "আমার দেখা নয়াচীন",
"d": "আমার কিছু কথা"
},
"correct_answer": "b",
"explanation": "বঙ্গবন্ধুর প্রথম বই 'অসমাপ্ত আত্মজীবনী' এবং দ্বিতীয় বই 'কারাগারের রোজনামচা' (২০১৭)।"
},
{
"id": 28,
"question": "বাংলাদেশ কত সালে ওআইসি (OIC)-এর সদস্যপদ লাভ করে?",
"options": {
"a": "১৯৭২",
"b": "১৯৭৩",
"c": "১৯৭৪",
"d": "১৯৭৫"
},
"correct_answer": "c",
"explanation": "১৯৭৪ সালের লাহোর সম্মেলনে বাংলাদেশ ওআইসি-এর সদস্যপদ লাভ করে।"
},
{
"id": 29,
"question": "বাংলাদেশে 'ভ্যাট' (VAT) চালু হয় কত সালে?",
"options": {
"a": "১৯৯১",
"b": "১৯৯৩",
"c": "১৯৯৬",
"d": "২০০১"
},
"correct_answer": "a",
"explanation": "১ জুলাই ১৯৯১ সাল থেকে বাংলাদেশে মূল্য সংযোজন কর (মূসক) বা ভ্যাট চালু হয়।"
},
{
"id": 30,
"question": "জাতীয় স্মৃতিসৌধের স্থপতি কে?",
"options": {
"a": "হামিদুর রহমান",
"b": "মাইনুল হোসেন",
"c": "শামসুল আলম",
"d": "তানভীর কবীর"
},
"correct_answer": "b",
"explanation": "সাভারে অবস্থিত জাতীয় স্মৃতিসৌধের স্থপতি সৈয়দ মাইনুল হোসেন।"
},
{
"id": 31,
"question": "বাংলাদেশের সবচেয়ে উঁচ পাহাড় চূড়ার নাম কী?",
"options": {
"a": "কেওক্রাডং",
"b": "তাজিংডং",
"c": "সাকা হাফং",
"d": "গারো পাহাড়"
},
"correct_answer": "b",
"explanation": "তাজিংডং (বিজয়) বর্তমানে বাংলাদেশের সর্বোচ্চ পাহাড় চূড়া হিসেবে স্বীকৃত।"
},
{
"id": 32,
"question": "বীরশ্রেষ্ঠ মতিউর রহমানের সমাধি কোথায় ছিল (বাংলাদেশে আনার আগে)?",
"options": {
"a": "করাচি",
"b": "রাওয়ালপিন্ডি",
"c": "লাহোর",
"d": "পেশোয়ার"
},
"correct_answer": "a",
"explanation": "বীরশ্রেষ্ঠ মতিউর রহমানের সমাধি পাকিস্তানের করাচির মাশরুর বেসে ছিল।"
},
{
"id": 33,
"question": "গৌড়-এর সোনা মসজিদ নির্মাণ করেন কে?",
"options": {
"a": "আলাউদ্দিন হোসেন শাহ",
"b": "শায়েস্তা খাঁ",
"c": "সুলতান গিয়াসউদ্দিন",
"d": "ইশা খাঁ"
},
"correct_answer": "a",
"explanation": "আলাউদ্দিন হোসেন শাহ ছোট সোনা মসজিদ নির্মাণ করেন।"
},
{
"id": 34,
"question": "বাংলাদেশের কোন জেলায় চা বাগান সবচেয়ে বেশি?",
"options": {
"a": "সিলেট",
"b": "মৌলভীবাজার",
"c": "হবিগঞ্জ",
"d": "পঞ্চগড়"
},
"correct_answer": "b",
"explanation": "মৌলভীবাজার জেলায় বাংলাদেশের সর্বাধিক চা বাগান অবস্থিত।"
},
{
"id": 35,
"question": "বঙ্গবন্ধু স্যাটেলাইট-১ কোন দেশের সহায়তায় নির্মিত হয়েছে?",
"options": {
"a": "যুক্তরাষ্ট্র",
"b": "ফ্রান্স",
"c": "রাশিয়া",
"d": "চীন"
},
"correct_answer": "b",
"explanation": "ফ্রান্সের থ্যালাস অ্যালেনিয়া স্পেস বঙ্গবন্ধু স্যাটেলাইট-১ নির্মাণ করে।"
},
{
"id": 36,
"question": "বাংলাদেশের প্রথম আদশশুমারি (জনশুমারি) হয় কবে?",
"options": {
"a": "১৯৭১",
"b": "১৯৭২",
"c": "১৯৭৪",
"d": "১৯৮১"
},
"correct_answer": "c",
"explanation": "স্বাধীন বাংলাদেশে প্রথম জনশুমারি অনুষ্ঠিত হয় ১৯৭৪ সালে।"
},
{
"id": 37,
"question": "কুয়াকাটা সমুদ্র সৈকতের দৈর্ঘ্য কত?",
"options": {
"a": "১২ কিমি",
"b": "১৮ কিমি",
"c": "৩০ কিমি",
"d": "১২০ কিমি"
},
"correct_answer": "b",
"explanation": "কুয়াকাটা সমুদ্র সৈকতের দৈর্ঘ্য প্রায় ১৮ কিলোমিটার।"
},
{
"id": 38,
"question": "বাংলাদেশে 'গাস' (GAS) ক্ষেত্র প্রথম আবিষ্কৃত হয় কোথায়?",
"options": {
"a": "হরিপুর",
"b": "সিলেট",
"c": "ব্রাহ্মণবাড়িয়া",
"d": "ফেঞ্চুগঞ্জ"
},
"correct_answer": "a",
"explanation": "১৯৫৫ সালে সিলেটের হরিপুরে প্রথম গ্যাস ক্ষেত্র আবিষ্কৃত হয়।"
},
{
"id": 39,
"question": "কোন এলাকাকে 'বাংলাদেশের ফুসফুস' বলা হয়?",
"options": {
"a": "সুন্দরবন",
"b": "ভাওয়াল গড়",
"c": "রাতারগুল",
"d": "হাকালুকি"
},
"correct_answer": "a",
"explanation": "পরিবেশগত গুরুত্বপূর্ণ ভূমিকার কারণে সুন্দরবনকে বাংলাদেশের ফুসফুস বলা হয়।"
},
{
"id": 40,
"question": "বাংলাদেশের কোন উপজাতি 'মাতৃতান্ত্রিক' সমাজব্যবস্থা অনুসরণ করে?",
"options": {
"a": "মারমা",
"b": "খাসিয়া",
"c": "চাকমা",
"d": "সাঁওতাল"
},
"correct_answer": "b",
"explanation": "গারো ও খাসিয়া উপজাতিদের সমাজ মাতৃতান্ত্রিক।"
},
{
"id": 41,
"question": "বাংলার প্রাচীন জনপদ 'পুন্ড্র'-এর বর্তমান অবস্থান কোথায়?",
"options": {
"a": "সিলেট",
"b": "বগুড়া",
"c": "দিনাজপুর",
"d": "কুমিল্লা"
},
"correct_answer": "b",
"explanation": "বগুড়ার মহাস্থানগড় প্রাচীন পুন্ড্রনগরের ধ্বংসাবশেষ।"
},
{
"id": 42,
"question": "বাংলাদেশের সংবিধান এ পর্যন্ত কতবার সংশোধন করা হয়েছে?",
"options": {
"a": "১৫ বার",
"b": "১৬ বার",
"c": "১৭ বার",
"d": "১৮ বার"
},
"correct_answer": "c",
"explanation": "বাংলাদেশের সংবিধান এ পর্যন্ত ১৭ বার সংশোধন করা হয়েছে।"
},
{
"id": 43,
"question": "পদ্মা নদী মেঘনার সাথে মিলিত হয়েছে কোথায়?",
"options": {
"a": "গোয়ালন্দ",
"b": "চাঁদপুর",
"c": "ভৈরব",
"d": "শরীয়তপুর"
},
"correct_answer": "b",
"explanation": "পদ্মা ও মেঘনা নদী চাঁদপুরের কাছে মিলিত হয়েছে।"
},
{
"id": 44,
"question": "বাংলাদেশের প্রথম জাতীয় সংসদ নির্বাচন অনুষ্ঠিত হয় কবে?",
"options": {
"a": "৭ মার্চ ১৯৭৩",
"b": "১০ এপ্রিল ১৯৭২",
"c": "১৬ ডিসেম্বর ১৯৭৩",
"d": "১৫ আগস্ট ১৯৭৫"
},
"correct_answer": "a",
"explanation": "১৯৭৩ সালের ৭ মার্চ বাংলাদেশের প্রথম সাধারণ নির্বাচন অনুষ্ঠিত হয়।"
},
{
"id": 45,
"question": "ঢাকা কবে প্রথম বাংলার রাজধানী হয়েছিল?",
"options": {
"a": "১৬০৮",
"b": "১৬১০",
"c": "১৯০৫",
"d": "১৯৪৭"
},
"correct_answer": "b",
"explanation": "১৬১০ সালে সুবাদার ইসলাম খাঁ ঢাকা প্রথম রাজধানী করেন (জাহাঙ্গীরনগর)।"
},
{
"id": 46,
"question": "লালবাগ কেল্লার অভ্যন্তরে কার সমাধি অবস্থিত?",
"options": {
"a": "শায়েস্তা খাঁ",
"b": "পরী বিবি",
"c": "নূরজাহান",
"d": "মমতাজ"
},
"correct_answer": "b",
"explanation": "শায়েস্তা খাঁর কন্যা ইরান দুখত (পরী বিবি)-এর সমাধি লালবাগ কেল্লায় অবস্থিত।"
},
{
"id": 47,
"question": "বাংলাদেশের সাথে ভারত ও মিয়ানমার—উভয় দেশের সীমান্ত রয়েছে কোন জেলার?",
"options": {
"a": "বান্দরবান",
"b": "খাগড়াছড়ি",
"c": "রাঙামাটি",
"d": "কক্সবাজার"
},
"correct_answer": "c",
"explanation": "রাঙামাটি জেলাটি ভারত ও মিয়ানমার উভয়ের সাথে সীমান্ত ভাগ করে।"
},
{
"id": 48,
"question": "মুক্তিযোদ্ধাদের অবদানের স্বীকৃতিস্বরূপ রাষ্ট্রীয় পুরস্কার কয়টি?",
"options": {
"a": "৩টি",
"b": "৪টি",
"c": "৫টি",
"d": "৭টি"
},
"correct_answer": "b",
"explanation": "বীরশ্রেষ্ঠ, বীর উত্তম, বীর বিক্রম ও বীর প্রতীক—এই ৪টি রাষ্ট্রীয় পুরস্কার দেওয়া হয়।"
},
{
"id": 49,
"question": "বাংলাদেশের 'রাষ্ট্রপতি' কার নিকট পদত্যাগপত্র জমা দেন?",
"options": {
"a": "প্রধানমন্ত্রী",
"b": "স্পিকার",
"c": "প্রধান বিচারপতি",
"d": "সংসদ উপনেতা"
},
"correct_answer": "b",
"explanation": "সংবিধান অনুযায়ী রাষ্ট্রপতি স্পিকারের উদ্দেশ্যে স্বাক্ষরযুক্ত পত্রের মাধ্যমে পদত্যাগ করতে পারেন।"
},
{
"id": 50,
"question": "ঢাকা বিশ্ববিদ্যালয়ের প্রথম উপাচার্য কে ছিলেন?",
"options": {
"a": "ড. এ এফ রহমান",
"b": "পি জে হার্টগ",
"c": "ড. জহির রায়হান",
"d": "স্যার সলিমুল্লাহ"
},
"correct_answer": "b",
"explanation": "স্যার ফিলিপ জেমস হার্টগ (P. J. Hartog) ছিলেন ঢাকা বিশ্ববিদ্যালয়ের প্রথম ভিসি।"
},
{
"id": 51,
"question": "বাংলাদেশের সংবিধানের 'মৌলিক অধিকার' সংরক্ষণকারী অনুচ্ছেদ কোনটি?",
"options": {
"a": "২৬ নম্বর",
"b": "২৭ নম্বর",
"c": "৪৪ নম্বর",
"d": "১০২ নম্বর"
},
"correct_answer": "c",
"explanation": "৪৪ নম্বর অনুচ্ছেদে মৌলিক অধিকার বলবৎ করার অধিকার দেওয়া হয়েছে এবং ১০২ নম্বর অনুচ্ছেদে রিট করার ক্ষমতা দেওয়া হয়েছে।"
},
{
"id": 52,
"question": "মুক্তিযুদ্ধের সময় 'অপারেশন জ্যাকপট' কোন ধরনের অভিযান ছিল?",
"options": {
"a": "স্থল অভিযান",
"b": "বিমান অভিযান",
"c": "নৌ-কমান্ডো অভিযান",
"d": "গেরিলা অভিযান"
},
"correct_answer": "c",
"explanation": "অপারেশন জ্যাকপট ছিল ১৯৭১ সালের ১৫ আগস্ট পরিচালিত মুক্তিযোদ্ধাদের একটি সফল নৌ-কমান্ডো অভিযান।"
},
{
"id": 53,
"question": "বাংলাদেশের প্রথম নারী নির্বাচন কমিশনার কে?",
"options": {
"a": "বেগম রোকেয়া",
"b": "বেগম কবিতা খানম",
"c": "সেলিনা হোসেন",
"d": "জাহানারা ইমাম"
},
"correct_answer": "b",
"explanation": "বেগম কবিতা খানম বাংলাদেশের ইতিহাসে প্রথম নারী নির্বাচন কমিশনার হিসেবে দায়িত্ব পালন করেন।"
},
{
"id": 54,
"question": "কান্তজিউ মন্দির কোন জেলায় অবস্থিত?",
"options": {
"a": "বগুড়া",
"b": "নাটোর",
"c": "দিনাজপুর",
"d": "রংপুর"
},
"correct_answer": "c",
"explanation": "টেরাকোটা শিল্পের জন্য বিখ্যাত কান্তজিউ মন্দির দিনাজপুর জেলার কাহারোল উপজেলায় অবস্থিত।"
},
{
"id": 55,
"question": "মহাস্থানগড় কোন নদীর তীরে অবস্থিত?",
"options": {
"a": "যমুনা",
"b": "তিস্তা",
"c": "করতোয়া",
"d": "আত্রাই"
},
"correct_answer": "c",
"explanation": "প্রাচীন পুণ্ড্রবর্ধনের রাজধানী মহাস্থানগড় বগুড়া জেলার করতোয়া নদীর তীরে অবস্থিত।"
},
{
"id": 56,
"question": "বাংলাদেশের বৃহত্তম তাপবিদ্যুৎ কেন্দ্র কোনটি?",
"options": {
"a": "আশুগঞ্জ",
"b": "ঘোড়াশাল",
"c": "পায়রা",
"d": "রামপাল"
},
"correct_answer": "c",
"explanation": "পটুয়াখালীর পায়রা তাপবিদ্যুৎ কেন্দ্র বর্তমানে বাংলাদেশের বৃহত্তম বিদ্যুৎ উৎপাদন কেন্দ্র।"
},
{
"id": 57,
"question": "বঙ্গবন্ধুকে 'বঙ্গবন্ধু' উপাধি দেওয়া হয় কোথায়?",
"options": {
"a": "পল্টন ময়দানে",
"b": "সোহরাওয়ার্দী উদ্যানে (রেসকোর্স)",
"c": "ঢাকা বিশ্ববিদ্যালয়ে",
"d": "কারাগারের ভেতর"
},
"correct_answer": "b",
"explanation": "১৯৬৯ সালের ২৩ ফেব্রুয়ারি রেসকোর্স ময়দানে ছাত্র সংগ্রাম পরিষদ শেখ মুজিবুর রহমানকে এই উপাধি দেয়।"
},
{
"id": 58,
"question": "বাংলাদেশের সাথে কয়টি দেশের স্থল সীমান্ত রয়েছে?",
"options": {
"a": "১টি",
"b": "২টি",
"c": "৩টি",
"d": "৪টি"
},
"correct_answer": "b",
"explanation": "বাংলাদেশের সাথে ভারত ও মায়ানমার—এই দুটি দেশের স্থল সীমান্ত রয়েছে।"
},
{
"id": 59,
"question": "জাতীয় স্মৃতিসৌধের ফলক কয়টি?",
"options": {
"a": "৫টি",
"b": "৬টি",
"c": "৭টি",
"d": "৯টি"
},
"correct_answer": "c",
"explanation": "জাতীয় স্মৃতিসৌধের ৭টি স্তম্ভ বা দেয়াল ১৯৫২ থেকে ১৯৭১ পর্যন্ত আন্দোলনের ৭টি পর্যায়কে নির্দেশ করে।"
},
{
"id": 60,
"question": "বাংলাদেশে প্রথম সার কারখানা স্থাপিত হয় কোথায়?",
"options": {
"a": "ঘোড়াশাল",
"b": "ফেঞ্চুগঞ্জ",
"c": "আশুগঞ্জ",
"d": "চট্টগ্রাম"
},
"correct_answer": "b",
"explanation": "১৯৬১ সালে সিলেটের ফেঞ্চুগঞ্জে ন্যাচারাল গ্যাস ফার্টিলাইজার ফ্যাক্টরি লিমিটেড স্থাপিত হয়।"
},
{
"id": 61,
"question": "গণপ্রজাতন্ত্রী বাংলাদেশের রাষ্ট্রপতি হওয়ার নূন্যতম বয়স কত?",
"options": {
"a": "২৫ বছর",
"b": "৩০ বছর",
"c": "৩৫ বছর",
"d": "৪০ বছর"
},
"correct_answer": "c",
"explanation": "সংবিধান অনুযায়ী রাষ্ট্রপতি হওয়ার জন্য বয়স কমপক্ষে ৩৫ বছর হতে হয়।"
},
{
"id": 62,
"question": "বাংলাদেশের সর্ব উত্তরের জায়গার নাম কী?",
"options": {
"a": "তেঁতুলিয়া",
"b": "বাংলাবান্ধা",
"c": "জায়গীরজোত",
"d": "মাঝগ্রাম"
},
"correct_answer": "b",
"explanation": "সর্ব উত্তরের থানা তেঁতুলিয়া হলেও নির্দিষ্ট স্থানের নাম বাংলাবান্ধা বা জায়গীরজোত।"
},
{
"id": 63,
"question": "বাংলাদেশের সংবিধান প্রণয়ন কমিটির একমাত্র মহিলা সদস্য কে ছিলেন?",
"options": {
"a": "বেগম রোকেয়া",
"b": "বেগম রাজিয়া বানু",
"c": "বেগম সুফিয়া কামাল",
"d": "আইভী রহমান"
},
"correct_answer": "b",
"explanation": "৩৪ সদস্য বিশিষ্ট সংবিধান প্রণয়ন কমিটির একমাত্র নারী সদস্য ছিলেন বেগম রাজিয়া বানু।"
},
{
"id": 64,
"question": "বরেন্দ্র জাদুঘর কোথায় অবস্থিত?",
"options": {
"a": "বগুড়া",
"b": "রাজশাহী",
"c": "রংপুর",
"d": "ঢাকা"
},
"correct_answer": "b",
"explanation": "বরেন্দ্র গবেষণা জাদুঘর বাংলাদেশের প্রাচীনতম জাদুঘর, যা রাজশাহী শহরে অবস্থিত।"
},
{
"id": 65,
"question": "বাংলাদেশের 'জাতীয় শিশু দিবস' কবে পালন করা হয়?",
"options": {
"a": "১০ জানুয়ারি",
"b": "১৭ মার্চ",
"c": "২৬ মার্চ",
"d": "১৪ এপ্রিল"
},
"correct_answer": "b",
"explanation": "বঙ্গবন্ধু শেখ মুজিবুর রহমানের জন্মদিন উপলক্ষে ১৭ মার্চ জাতীয় শিশু দিবস পালন করা হয়।"
},
{
"id": 66,
"question": "বাংলাদেশের কোন নদীকে 'প্রাকৃতিক মৎস্য প্রজনন কেন্দ্র' বলা হয়?",
"options": {
"a": "পদ্মা",
"b": "মেঘনা",
"c": "হালদা",
"d": "কর্ণফুলী"
},
"correct_answer": "c",
"explanation": "চট্টগ্রামের হালদা নদী এশিয়ার অন্যতম বৃহৎ প্রাকৃতিক মৎস্য প্রজনন কেন্দ্র।"
},
{
"id": 67,
"question": "বাংলাদেশের রণসংগীতের রচয়িতা কে?",
"options": {
"a": "রবীন্দ্রনাথ ঠাকুর",
"b": "কাজী নজরুল ইসলাম",
"c": "জসীমউদ্দীন",
"d": "ডি এল রায়"
},
"correct_answer": "b",
"explanation": "কাজী নজরুল ইসলামের 'চল চল চল' কবিতাটি বাংলাদেশের রণসংগীত।"
},
{
"id": 68,
"question": "একনেক (ECNEC)-এর চেয়ারম্যান কে?",
"options": {
"a": "অর্থমন্ত্রী",
"b": "পরিকল্পনামন্ত্রী",
"c": "প্রধানমন্ত্রী",
"d": "গভর্নর"
},
"correct_answer": "c",
"explanation": "জাতীয় অর্থনৈতিক পরিষদের নির্বাহী কমিটি বা একনেক-এর প্রধান হলেন প্রধানমন্ত্রী।"
},
{
"id": 69,
"question": "১৯৭১ সালের ১০ এপ্রিল গঠিত অস্থায়ী সরকারের রাষ্ট্রপতি কে ছিলেন?",
"options": {
"a": "তাজউদ্দীন আহমদ",
"b": "সৈয়দ নজরুল ইসলাম",
"c": "বঙ্গবন্ধু শেখ মুজিবুর রহমান",
"d": "খন্দকার মোশতাক আহমেদ"
},
"correct_answer": "c",
"explanation": "মুজিবনগর সরকারের রাষ্ট্রপতি ছিলেন শেখ মুজিবুর রহমান, তবে তার অনুপস্থিতিতে সৈয়দ নজরুল ইসলাম অস্থায়ী রাষ্ট্রপতি ছিলেন।"
},
{
"id": 70,
"question": "বাংলাদেশের পতাকার দৈর্ঘ্য ও প্রস্থের অনুপাত কত?",
"options": {
"a": "৩:২",
"b": "৫:৩",
"c": "১০:৬",
"d": "সবগুলোই সঠিক"
},
"correct_answer": "d",
"explanation": "প্রাথমিক অনুপাত ১০:৬, যা ৫:৩ বা ৫/৩ আকারেও লেখা যায়।"
},
{
"id": 71,
"question": "বাংলাদেশের সাথে ভারতের কয়টি রাজ্যের সীমান্ত রয়েছে?",
"options": {
"a": "৩টি",
"b": "৪টি",
"c": "৫টি",
"d": "৬টি"
},
"correct_answer": "c",
"explanation": "রাজ্যগুলো হলো: পশ্চিমবঙ্গ, মেঘালয়, মিজোরাম, ত্রিপুরা এবং আসাম।"
},
{
"id": 72,
"question": "বাংলা পিডিয়ার প্রধান সম্পাদক কে?",
"options": {
"a": "ড. মুহাম্মদ শহীদুল্লাহ",
"b": "ড. সিরাজুল ইসলাম",
"c": "ড. আনিসুজ্জামান",
"d": "আব্দুল্লাহ আবু সায়ীদ"
},
"correct_answer": "b",
"explanation": "ড. সিরাজুল ইসলাম এশিয়াটিক সোসাইটি প্রকাশিত বাংলাপিডিয়ার প্রধান সম্পাদক।"
},
{
"id": 73,
"question": "বাংলাদেশে মোট কয়টি সমুদ্র বন্দর রয়েছে?",
"options": {
"a": "২টি",
"b": "৩টি",
"c": "৪টি",
"d": "৫টি"
},
"correct_answer": "b",
"explanation": "বন্দর তিনটি হলো: চট্টগ্রাম, মোংলা এবং পায়রা সমুদ্র বন্দর।"
},
{
"id": 74,
"question": "বাংলাদেশের দীর্ঘতম নদীর নাম কী?",
"options": {
"a": "পদ্মা",
"b": "মেঘনা",
"c": "যমুনা",
"d": "ব্রহ্মপুত্র"
},
"correct_answer": "b",
"explanation": "মেঘনা বাংলাদেশের দীর্ঘতম, প্রশস্ততম ও গভীরতম নদী।"
},
{
"id": 75,
"question": "বাংলা নববর্ষ 'পহেলা বৈশাখ' প্রবর্তন করেছিলেন কে?",
"options": {
"a": "লক্ষণ সেন",
"b": "আকবর",
"c": "শের শাহ",
"d": "ঈশা খাঁ"
},
"correct_answer": "b",
"explanation": "মুঘল সম্রাট আকবর খাজনা আদায়ের সুবিধার্থে ফসলি সন বা বাংলা সন প্রবর্তন করেন।"
},
{
"id": 76,
"question": "জাতীয় সংসদের 'কোরাম' হয় কতজন সদস্য উপস্থিত থাকলে?",
"options": {
"a": "৫০ জন",
"b": "৬০ জন",
"c": "৮০ জন",
"d": "১০০ জন"
},
"correct_answer": "b",
"explanation": "কমপক্ষে ৬০ জন সংসদ সদস্য উপস্থিত থাকলে সংসদের কোরাম হয়।"
},
{
"id": 77,
"question": "বাংলাদেশের বৃহত্তম বনভূমি কোনটি?",
"options": {
"a": "সুন্দরবন",
"b": "সিলেট বনাঞ্চল",
"c": "পার্বত্য চট্টগ্রাম বনাঞ্চল",
"d": "ভাওয়াল গড়"
},
"correct_answer": "c",
"explanation": "আয়তনের দিক থেকে পার্বত্য চট্টগ্রামের পাহাড়ি বনভূমি বাংলাদেশের বৃহত্তম বনভূমি।"
},
{
"id": 78,
"question": "মুক্তিযুদ্ধের সর্বোচ্চ বীরত্বসূচক খেতাব 'বীরশ্রেষ্ঠ' গেজেট অনুযায়ী কার নাম তালিকার প্রথমে?",
"options": {
"a": "মতিউর রহমান",
"b": "মহিউদ্দিন জাহাঙ্গীর",
"c": "মুন্সী আব্দুর রউফ",
"d": "নূর মোহাম্মদ শেখ"
},
"correct_answer": "b",
"explanation": "বীরশ্রেষ্ঠদের গেজেট তালিকায় প্রথমে নাম রয়েছে ক্যাপ্টেন মহিউদ্দিন জাহাঙ্গীরের।"
},
{
"id": 79,
"question": "শহীদ বুদ্ধিজীবী দিবস পালিত হয় কবে?",
"options": {
"a": "৭ মার্চ",
"b": "১০ ডিসেম্বর",
"c": "১৪ ডিসেম্বর",
"d": "১৬ ডিসেম্বর"
},
"correct_answer": "c",
"explanation": "১৯৭১ সালের ১৪ ডিসেম্বর পাকিস্তান বাহিনী শ্রেষ্ঠ সন্তানদের হত্যা করে, তাই এই দিনটি শোকাবহ বুদ্ধিজীবী দিবস।"
},
{
"id": 80,
"question": "বাংলাদেশের প্রথম নারী স্পিকারের নাম কী?",
"options": {
"a": "আইভী রহমান",
"b": "ড. শিরীন শারমিন চৌধুরী",
"c": "সেলিনা হোসেন",
"d": "দীপুমনি"
},
"correct_answer": "b",
"explanation": "ড. শিরীন শারমিন চৌধুরী নবম সংসদের শেষ দিকে বাংলাদেশের প্রথম নারী স্পিকার হিসেবে নির্বাচিত হন।"
},
{
"id": 81,
"question": "বাংলাদেশের একমাত্র প্রবাল দ্বীপ কোনটি?",
"options": {
"a": "সন্দ্বীপ",
"b": "হাতিয়া",
"c": "সেন্টমার্টিন",
"d": "মৌলভীবাজার"
},
"correct_answer": "c",
"explanation": "সেন্টমার্টিন হলো বাংলাদেশের একমাত্র প্রবাল দ্বীপ যা কক্সবাজার জেলায় অবস্থিত।"
},
{
"id": 82,
"question": "বাংলাদেশের সংবিধানে কয়টি ভাগ বা অধ্যায় রয়েছে?",
"options": {
"a": "৭টি",
"b": "৯টি",
"c": "১১টি",
"d": "১৩টি"
},
"correct_answer": "c",
"explanation": "বাংলাদেশের সংবিধানে ১১টি ভাগ, ১৫৩টি অনুচ্ছেদ এবং ১টি প্রস্তাবনা রয়েছে।"
},
{
"id": 83,
"question": "বাংলাদেশের চা গবেষণা ইনস্টিটিউট (BTRI) কোথায় অবস্থিত?",
"options": {
"a": "শ্রীমঙ্গল",
"b": "সিলেট",
"c": "চট্টগ্রাম",
"d": "পঞ্চগড়"
},
"correct_answer": "a",
"explanation": "মৌলভীবাজারের শ্রীমঙ্গলে বাংলাদেশ চা গবেষণা ইনস্টিটিউট অবস্থিত।"
},
{
"id": 84,
"question": "মুজিবনগর স্মৃতিসৌধের স্থপতি কে?",
"options": {
"a": "সৈয়দ মাইনুল হোসেন",
"b": "তানভীর কবীর",
"c": "মুস্তফা মনোয়ার",
"d": "শামসুল আলম"
},
"correct_answer": "b",
"explanation": "মেহেরপুর জেলার মুজিবনগরে অবস্থিত স্মৃতিসৌধের স্থপতি তানভীর কবীর।"
},
{
"id": 85,
"question": "কোনটি 'নিঝুম দ্বীপ'-এর পূর্ব নাম ছিল?",
"options": {
"a": "চর ওসমান",
"b": "চর পীর",
"c": "চর আলেকজান্ডার",
"d": "চর বাদাম"
},
"correct_answer": "a",
"explanation": "নোয়াখালীর নিঝুম দ্বীপের পূর্ব নাম ছিল চর ওসমান বা বাউলার চর।"
},
{
"id": 86,
"question": "বাংলাদেশের বৃহত্তম কয়লা খনি কোথায় অবস্থিত?",
"options": {
"a": "বড়পুকুরিয়া, দিনাজপুর",
"b": "খালাসপীর, রংপুর",
"c": "জয়পুরহাট",
"d": "জামালগঞ্জ"
},
"correct_answer": "a",
"explanation": "দিনাজপুরের বড়পুকুরিয়ায় বাংলাদেশের বৃহত্তম এবং একমাত্র উৎপাদনশীল কয়লা খনি অবস্থিত।"
},
{
"id": 87,
"question": "বাংলাদেশে বর্তমানে মোট কয়টি সিটি কর্পোরেশন রয়েছে?",
"options": {
"a": "১০টি",
"b": "১১টি",
"c": "১২টি",
"d": "১৩টি"
},
"correct_answer": "c",
"explanation": "সর্বশেষ সিটি কর্পোরেশন হলো ময়মনসিংহ। মোট সিটি কর্পোরেশনের সংখ্যা ১২টি।"
},
{
"id": 88,
"question": "বাংলাদেশের জাতীয় বৃক্ষের নাম কী?",
"options": {
"a": "কাঠাল গাছ",
"b": "বট গাছ",
"c": "আম গাছ",
"d": "নারিকেল গাছ"
},
"correct_answer": "c",
"explanation": "২০১০ সালে আম গাছকে বাংলাদেশের জাতীয় বৃক্ষ হিসেবে ঘোষণা করা হয়।"
},
{
"id": 89,
"question": "বাংলাদেশের সর্বোচ্চ বেসামরিক পুরস্কার কোনটি?",
"options": {
"a": "একুশে পদক",
"b": "স্বাধীনতা পদক",
"c": "বাংলা একাডেমি পুরস্কার",
"d": "জাতীয় চলচ্চিত্র পুরস্কার"
},
"correct_answer": "b",
"explanation": "স্বাধীনতা পদক বাংলাদেশের সর্বোচ্চ রাষ্ট্রীয় বেসামরিক সম্মাননা।"
},
{
"id": 90,
"question": "বিখ্যাত 'মনপুরা-৭০' কী?",
"options": {
"a": "একটি উপন্যাস",
"b": "একটি চিত্রকর্ম",
"c": "একটি চলচ্চিত্র",
"d": "একটি কবিতা"
},
"correct_answer": "b",
"explanation": "মনপুরা-৭০ হলো শিল্পাচার্য জয়নুল আবেদিনের আঁকা একটি বিখ্যাত চিত্রকর্ম।"
},
{
"id": 91,
"question": "বঙ্গবন্ধুর স্বদেশ প্রত্যাবর্তন দিবস কোনটি?",
"options": {
"a": "৮ জানুয়ারি",
"b": "১০ জানুয়ারি",
"c": "২৬ মার্চ",
"d": "১৬ ডিসেম্বর"
},
"correct_answer": "b",
"explanation": "১৯৭২ সালের ১০ জানুয়ারি বঙ্গবন্ধু পাকিস্তানের কারাগার থেকে মুক্ত হয়ে বাংলাদেশে ফেরেন।"
},
{
"id": 92,
"question": "বাংলাদেশের প্রথম ভূ-উপগ্রহ কেন্দ্রটি কোথায় অবস্থিত?",
"options": {
"a": "গাজীপুর",
"b": "বেতবুনিয়া",
"c": "তালিবাবাদ",
"d": "মহাখালী"
},
"correct_answer": "b",
"explanation": "১৯৭৫ সালে রাঙামাটির বেতবুনিয়ায় প্রথম ভূ-উপগ্রহ কেন্দ্রটি উদ্বোধন করা হয়।"
},
{
"id": 93,
"question": "সার্ক (SAARC) গঠনের উদ্যোগ নিয়েছিলেন কে?",
"options": {
"a": "শেখ মুজিবুর রহমান",
"b": "জিয়াউর রহমান",
"c": "তাজউদ্দীন আহমদ",
"d": "এইচ এম এরশাদ"
},
"correct_answer": "b",
"explanation": "সাবেক প্রেসিডেন্ট জিয়াউর রহমান প্রথম দক্ষিণ এশীয় দেশগুলোর মধ্যে আঞ্চলিক সহযোগিতা সংস্থার ধারণা দেন।"
},
{
"id": 94,
"question": "বাংলাদেশের সবচেয়ে ছোট বিভাগ কোনটি?",
"options": {
"a": "সিলেট",
"b": "রংপুর",
"c": "ময়মনসিংহ",
"d": "বরিশাল"
},
"correct_answer": "c",
"explanation": "আয়তন ও জনসংখ্যা উভয় দিক থেকেই ময়মনসিংহ বাংলাদেশের ক্ষুদ্রতম বিভাগ।"
},
{
"id": 95,
"question": "মুক্তিযুদ্ধের সময় 'সেক্টর-১০' এর বিশেষত্ব কী ছিল?",
"options": {
"a": "কোনো নিয়মিত সেক্টর কমান্ডার ছিল না",
"b": "এটি নৌ-কমান্ডোদের অধীনে ছিল",
"c": "পুরো বাংলাদেশ ছিল এর অধীনে",
"d": "সবগুলো সঠিক"
},
"correct_answer": "d",
"explanation": "সেক্টর ১০-এর কোনো নিয়মিত কমান্ডার ছিল না এবং এটি ছিল নৌ-কমান্ডোদের বিশেষ সেক্টর।"
},
{
"id": 96,
"question": "বাংলা পিডিয়া কয়টি ভাষায় প্রকাশিত?",
"options": {
"a": "১টি",
"b": "২টি",
"c": "৩টি",
"d": "৪টি"
},
"correct_answer": "b",
"explanation": "বাংলাপিডিয়া বাংলা ও ইংরেজি—এই দুই ভাষায় প্রকাশিত।"
},
{
"id": 97,
"question": "ময়নামতি কোথায় অবস্থিত?",
"options": {
"a": "সিলেট",
"b": "কুমিল্লা",
"c": "বগুড়া",
"d": "ঢাকা"
},
"correct_answer": "b",
"explanation": "কুমিল্লার ময়নামতিতে প্রাচীন বৌদ্ধ সভ্যতার ধ্বংসাবশেষ পাওয়া গেছে।"
},
{
"id": 98,
"question": "বাংলাদেশের সংবিধানের 'ব্যাখ্যাকারক' কে?",
"options": {
"a": "সংসদ",
"b": "রাষ্ট্রপতি",
"c": "সুপ্রিম কোর্ট",
"d": "আইন মন্ত্রণালয়"
},
"correct_answer": "c",
"explanation": "সুপ্রিম কোর্ট হলো বাংলাদেশের সংবিধানের একমাত্র ও চূড়ান্ত ব্যাখ্যাকারক।"
},
{
"id": 99,
"question": "বাংলাদেশ কত সালে জাতিসংঘের সদস্যপদ লাভ করে?",
"options": {
"a": "১৯৭২",
"b": "১৯৭৩",
"c": "১৯৭৪",
"d": "১৯৭৫"
},
"correct_answer": "c",
"explanation": "১৭ সেপ্টেম্বর ১৯৭৪ সালে বাংলাদেশ জাতিসংঘের ১৩৬তম সদস্য হিসেবে অন্তর্ভুক্ত হয়।"
},
{
"id": 100,
"question": "বীরশ্রেষ্ঠ হামিদুর রহমানের দেহাবশেষ কোথায় সমাহিত করা হয়েছে?",
"options": {
"a": "ভারতের আমবাসা",
"b": "মিরপুর শহীদ বুদ্ধিজীবী কবরস্থান",
"c": "বনানী কবরস্থান",
"d": "আজিমপুর কবরস্থান"
},
"correct_answer": "b",
"explanation": "হামিদুর রহমানের দেহাবশেষ ভারত থেকে এনে মিরপুর শহীদ বুদ্ধিজীবী কবরস্থানে সমাহিত করা হয়েছে।"
}
]
